LICENSE
README.md
setup.py
NeurIPS22_CellSeg.egg-info/PKG-INFO
NeurIPS22_CellSeg.egg-info/SOURCES.txt
NeurIPS22_CellSeg.egg-info/dependency_links.txt
NeurIPS22_CellSeg.egg-info/entry_points.txt
NeurIPS22_CellSeg.egg-info/requires.txt
NeurIPS22_CellSeg.egg-info/top_level.txt
baseline/__init__.py
baseline/model_training_3class.py
baseline/predict.py
baseline/unetr2d.py
baseline/data/__init__.py
baseline/data/pre_process_3class.py
baseline/data/model/unet_3class/20220708-2207_model_training_3class.py
baseline/data/model/unet_3class/20220710-1947_model_training_3class.py
baseline/data/model/unet_3class/20220710-2117_model_training_3class.py
baseline/models/__init__.py
baseline/work_dir/__init__.py