Metadata-Version: 2.1
Name: NeurIPS22-CellSeg
Version: 0.0.1
Summary: NeurIPS-CellSeg-baseline
Home-page: https://github.com/JunMa11/NeurIPS-CellSeg
Author: Cheng Ge
Author-email: 13851520957@163.com
License: MIT
Platform: all
License-File: LICENSE
